tests/__init__.py
tests/test_augs.py
tests/test_compatibility.py
tests/test_imageloaders.py
tests/test_maskfuncs.py
tests/test_multithreading.py
tests/test_patchsamplers.py
tests/test_samplers.py
tests/test_utils.py
tests/test_zarrdataset.py
tests/utils.py
zarrdataset/__init__.py
zarrdataset/_augs.py
zarrdataset/_imageloaders.py
zarrdataset/_maskfuncs.py
zarrdataset/_samplers.py
zarrdataset/_utils.py
zarrdataset/_zarrdataset.py
zarrdataset-0.2.2.dist-info/LICENSE
zarrdataset-0.2.2.dist-info/METADATA
zarrdataset-0.2.2.dist-info/WHEEL
zarrdataset-0.2.2.dist-info/top_level.txt
zarrdataset-0.2.2.dist-info/RECORD
