Metadata-Version: 2.1
Name: zarrdataset
Version: 0.2.2
Summary: Zarr-based dataset for PyTorch training pipelines. Written and maintained by the Research IT team at The Jackson Laboratory.
Home-page: https://github.com/TheJacksonLaboratory/zarrdataset
Maintainer: Fernando Cervantes
Maintainer-email: fernando.cervantes@jax.org
License: UNKNOWN
Platform: UNKNOWN
Requires-Python: >=3.9
License-File: LICENSE
Requires-Dist: requests>=2.31.0
Requires-Dist: aiohttp<4.0.0,>=3.7.4.post0
Requires-Dist: botocore<1.31.18,>=1.31.17
Requires-Dist: boto3<1.28.18,>=1.28.17
Requires-Dist: fsspec>=2023.9.2
Requires-Dist: s3fs>=0.4.2
Requires-Dist: zarr<3.0,>=2.12.0
Requires-Dist: scikit-image>=0.19.3
Requires-Dist: poisson-disc>=0.2.1
